MANIFEST.in
README.md
bakauditor.yml
setup.py
bakauditor/__init__.py
bakauditor/tools.py
bakauditor.egg-info/PKG-INFO
bakauditor.egg-info/SOURCES.txt
bakauditor.egg-info/dependency_links.txt
bakauditor.egg-info/requires.txt
bakauditor.egg-info/top_level.txt
bakauditor/plugins/__init__.py
bakauditor/plugins/borg.py
bakauditor/plugins/borg0.py
bakauditor/plugins/dir.py
bakauditor/plugins/dod.py
bakauditor/plugins/file.py
bakauditor/plugins/zfs.py
bin/bakauditor