Metadata-Version: 2.1
Name: bakauditor
Version: 0.0.15
Summary: Backup auditor
Home-page: https://github.com/divi255/bakauditor
Author: Sergei S.
Author-email: s@makeitwork.cz
License: MIT
Platform: UNKNOWN
Classifier: Programming Language :: Python :: 3
Classifier: License :: OSI Approved :: MIT License
Classifier: Topic :: System :: Archiving :: Backup
